ShiyanlouHadoopJiaochengHeji20160904Fix1/README.md
ShiyanlouHadoopJiaochengHeji20160904Fix1/__init__.py
ShiyanlouHadoopJiaochengHeji20160904Fix1/__main__.py
ShiyanlouHadoopJiaochengHeji20160904Fix1/file.epub
ShiyanlouHadoopJiaochengHeji20160904Fix1/index.html
ShiyanlouHadoopJiaochengHeji20160904Fix1/css/__init__.py
ShiyanlouHadoopJiaochengHeji20160904Fix1/css/annotations.css
ShiyanlouHadoopJiaochengHeji20160904Fix1/css/main.css
ShiyanlouHadoopJiaochengHeji20160904Fix1/css/normalize.css
ShiyanlouHadoopJiaochengHeji20160904Fix1/css/popup.css
ShiyanlouHadoopJiaochengHeji20160904Fix1/font/__init__.py
ShiyanlouHadoopJiaochengHeji20160904Fix1/font/fontello.eot
ShiyanlouHadoopJiaochengHeji20160904Fix1/font/fontello.svg
ShiyanlouHadoopJiaochengHeji20160904Fix1/font/fontello.ttf
ShiyanlouHadoopJiaochengHeji20160904Fix1/font/fontello.woff
ShiyanlouHadoopJiaochengHeji20160904Fix1/img/__init__.py
ShiyanlouHadoopJiaochengHeji20160904Fix1/img/annotator-glyph-sprite.png
ShiyanlouHadoopJiaochengHeji20160904Fix1/img/annotator-icon-sprite.png
ShiyanlouHadoopJiaochengHeji20160904Fix1/img/apple-touch-icon.png
ShiyanlouHadoopJiaochengHeji20160904Fix1/img/cancelfullscreen.png
ShiyanlouHadoopJiaochengHeji20160904Fix1/img/close.png
ShiyanlouHadoopJiaochengHeji20160904Fix1/img/fullscreen.png
ShiyanlouHadoopJiaochengHeji20160904Fix1/img/loader.gif
ShiyanlouHadoopJiaochengHeji20160904Fix1/img/menu-icon.png
ShiyanlouHadoopJiaochengHeji20160904Fix1/img/save.png
ShiyanlouHadoopJiaochengHeji20160904Fix1/img/saved.png
ShiyanlouHadoopJiaochengHeji20160904Fix1/img/settings-s.png
ShiyanlouHadoopJiaochengHeji20160904Fix1/img/settings.png
ShiyanlouHadoopJiaochengHeji20160904Fix1/img/star.png
ShiyanlouHadoopJiaochengHeji20160904Fix1/js/__init__.py
ShiyanlouHadoopJiaochengHeji20160904Fix1/js/epub.js
ShiyanlouHadoopJiaochengHeji20160904Fix1/js/epub.min.js
ShiyanlouHadoopJiaochengHeji20160904Fix1/js/epub.min.map
ShiyanlouHadoopJiaochengHeji20160904Fix1/js/hooks.min.js
shiyanlou_hadoop_jiaocheng_heji_20160904_fix1-2024.3.2.0.dist-info/METADATA
shiyanlou_hadoop_jiaocheng_heji_20160904_fix1-2024.3.2.0.dist-info/WHEEL
shiyanlou_hadoop_jiaocheng_heji_20160904_fix1-2024.3.2.0.dist-info/entry_points.txt
shiyanlou_hadoop_jiaocheng_heji_20160904_fix1-2024.3.2.0.dist-info/top_level.txt
shiyanlou_hadoop_jiaocheng_heji_20160904_fix1-2024.3.2.0.dist-info/RECORD
